# Python 2.7
# Embedded file name: /src/external-vcs/github/rocky/python-uncompyle6/__pkginfo__.py

   1       0	LOAD_CONST        'uncompyle6 packaging information'
           3	STORE_NAME        '__doc__'

  13       6	LOAD_CONST        '\nCopyright (C) 2015 Rocky Bernstein <rocky@gnu.org>.\n'
           9	STORE_NAME        'copyright'

  15      12	LOAD_CONST        'Development Status :: 3 - Alpha'

  16      15	LOAD_CONST        'Intended Audience :: Developers'

  17      18	LOAD_CONST        'Operating System :: OS Independent'

  18      21	LOAD_CONST        'Programming Language :: Python'

  19      24	LOAD_CONST        'Topic :: Software Development :: Debuggers'

  20      27	LOAD_CONST        'Topic :: Software Development :: Libraries :: Python Modules'
          30	BUILD_LIST_6      ''
          33	STORE_NAME        'classifiers'

  24      36	LOAD_CONST        'Rocky Bernstein'
          39	STORE_NAME        'author'

  25      42	LOAD_CONST        'rb@dustyfeet.com'
          45	STORE_NAME        'author_email'

  26      48	LOAD_CONST        ''
          51	STORE_NAME        'ftp_url'

  28      54	LOAD_CONST        'python-debugger@googlegroups.com'
          57	STORE_NAME        'mailing_list'

  29      60	LOAD_CONST        'uncompyle6'
          63	STORE_NAME        'modname'

  30      66	LOAD_CONST        'uncompyle6'
          69	LOAD_CONST        'uncompyle6.opcodes'
          72	BUILD_LIST_2      ''
          75	STORE_NAME        'packages'

  31      78	LOAD_CONST        ''
          81	STORE_NAME        'py_modules'

  32      84	LOAD_CONST        'Python byte-code disassembler and source-code converter'
          87	STORE_NAME        'short_desc'

  33      90	LOAD_CONST        'bin/uncompyle6'
          93	LOAD_CONST        'bin/pydisassemble'
          96	BUILD_LIST_2      ''
          99	STORE_NAME        'scripts'

  35     102	LOAD_CONST        -1
         105	LOAD_CONST        ''
         108	IMPORT_NAME       'os.path'
         111	STORE_NAME        'os'

  38     114	LOAD_CONST        '<code_object get_srcdir>'
         117	STOP_CODE         ''
         118	STOP_CODE         ''
         119	STORE_NAME        'get_srcdir'
         122	BUILD_MAP         ''
         125	STORE_NAME        'ns'
         128	LOAD_CONST        '2.0'
         131	STORE_NAME        'version'
         134	LOAD_CONST        'https://github.com/rocky/python-uncompyle6/'
         137	STORE_NAME        'web'
         140	LOAD_NAME         'True'
         143	STORE_NAME        'zip_safe'
         146	LOAD_CONST        '<code_object read>'
         149	STOP_CODE         ''
         150	STOP_CODE         ''
         151	STORE_NAME        'read'
         154	LOAD_NAME         'read'
         157	LOAD_CONST        'README.rst'
         160	POP_TOP           ''
         161	STOP_CODE         ''
         162	LOAD_CONST        '\n'
         165	BINARY_ADD        ''
         166	STORE_NAME        'long_description'
         169	LOAD_CONST        ''
         172	RETURN_VALUE      ''

